flask_sqlalchemy-stubs/METADATA.toml
flask_sqlalchemy-stubs/__init__.pyi
flask_sqlalchemy-stubs/model.pyi
flask_sqlalchemy-stubs/utils.pyi
types_Flask_SQLAlchemy-2.5.9.4.dist-info/METADATA
types_Flask_SQLAlchemy-2.5.9.4.dist-info/WHEEL
types_Flask_SQLAlchemy-2.5.9.4.dist-info/top_level.txt
types_Flask_SQLAlchemy-2.5.9.4.dist-info/RECORD
